opaclient/__init__.py
opaclient/client.py
opaclient/input.py
opaclient-0.1.0.dist-info/LICENSE
opaclient-0.1.0.dist-info/WHEEL
opaclient-0.1.0.dist-info/METADATA
opaclient-0.1.0.dist-info/RECORD
